Metadata-Version: 2.4
Name: django-tenant-schemas
Version: 2.0.0
Summary: Tenant support for Django using PostgreSQL schemas.
Author-email: Bernardo Pires Carneiro <carneiro.be@gmail.com>
License: MIT
Project-URL: Homepage, https://github.com/bcarneiro/django-tenant-schemas
Project-URL: Repository, https://github.com/bcarneiro/django-tenant-schemas
Classifier: License :: OSI Approved :: MIT License
Classifier: Framework :: Django
Classifier: Framework :: Django :: 4.2
Classifier: Framework :: Django :: 5.1
Classifier: Framework :: Django :: 5.2
Classifier: Programming Language :: Python
Classifier: Programming Language :: Python :: 3.8
Classifier: Programming Language :: Python :: 3.9
Classifier: Programming Language :: Python :: 3.10
Classifier: Programming Language :: Python :: 3.11
Classifier: Programming Language :: Python :: 3.12
Classifier: Programming Language :: Python :: 3.13
Classifier: Topic :: Database
Classifier: Topic :: Software Development :: Libraries
Requires-Python: >=3.8
License-File: LICENSE
Requires-Dist: Django>=4.2
Requires-Dist: ordered-set
Provides-Extra: psycopg2
Requires-Dist: psycopg2-binary; extra == "psycopg2"
Provides-Extra: psycopg
Requires-Dist: psycopg[binary]>=3.0; extra == "psycopg"
Dynamic: license-file
